setup.py
olut/__init__.py
olut/command.py
olut/version.py
olut.egg-info/PKG-INFO
olut.egg-info/SOURCES.txt
olut.egg-info/dependency_links.txt
olut.egg-info/entry_points.txt
olut.egg-info/requires.txt
olut.egg-info/top_level.txt
tests/__init__.py