Metadata-Version: 1.0
Name: olut
Version: 0.5.6
Summary: Olut is a packging framework meant for deploying applications
Home-page: https://github.com/samuel/olut
Author: Samuel Stauffer
Author-email: samuel@descolada.com
License: UNKNOWN
Platform: UNKNOWN
Classifier: Intended Audience :: Developers
Classifier: License :: OSI Approved :: BSD License
Classifier: Operating System :: OS Independent
Classifier: Programming Language :: Python
Classifier: Topic :: Software Development :: Libraries :: Python Modules
